myLib/myLib.py
kyeongmo230508AIL-0.0.3.dist-info/METADATA
kyeongmo230508AIL-0.0.3.dist-info/WHEEL
kyeongmo230508AIL-0.0.3.dist-info/top_level.txt
kyeongmo230508AIL-0.0.3.dist-info/RECORD
