Metadata-Version: 2.1
Name: kyeongmo230508AIL
Version: 0.0.3
Summary: AI Lib
Home-page: https://github.com/kimkyeongmo/myLib
Download-URL: https://github.com/kimkyeongmo/myLib/abc.zip
Author: kimkyeongmo
License: UNKNOWN
Platform: UNKNOWN
Classifier: Programming Language :: Python :: 3
